pyumdreplace.cp39-win32.pyd
pyumdreplace-0.1.0.dist-info/LICENSE
pyumdreplace-0.1.0.dist-info/METADATA
pyumdreplace-0.1.0.dist-info/WHEEL
pyumdreplace-0.1.0.dist-info/top_level.txt
pyumdreplace-0.1.0.dist-info/RECORD
