Metadata-Version: 2.1
Name: pyumdreplace
Version: 0.1.0
Summary: Python interface for UMD-replace.
Home-page: https://github.com/Illidanz/pyumdreplace
Author: Illidan
License: UNKNOWN
Platform: UNKNOWN
Classifier: Programming Language :: Python :: 3
Classifier: License :: OSI Approved :: GNU General Public License v3 (GPLv3)
License-File: LICENSE
